{
  "/_not-found/page": "app/_not-found/page.js",
  "/admin/dashboard/page": "app/admin/dashboard/page.js",
  "/admin/page": "app/admin/page.js",
  "/auth/login/page": "app/auth/login/page.js",
  "/auth/register/page": "app/auth/register/page.js",
  "/c/[token]/route": "app/c/[token]/route.js",
  "/chat/page": "app/chat/page.js",
  "/create-case/page": "app/create-case/page.js",
  "/dashboard/cases/page": "app/dashboard/cases/page.js",
  "/dashboard/page": "app/dashboard/page.js",
  "/debug-user/page": "app/debug-user/page.js",
  "/login/page": "app/login/page.js",
  "/notifications/page": "app/notifications/page.js",
  "/privacy-policy/page": "app/privacy-policy/page.js",
  "/provider/[id]/page": "app/provider/[id]/page.js",
  "/provider/chat/[conversationId]/page": "app/provider/chat/[conversationId]/page.js",
  "/provider/dashboard/page": "app/provider/dashboard/page.js",
  "/referrals/page": "app/referrals/page.js",
  "/register/page": "app/register/page.js",
  "/settings/sms/page": "app/settings/sms/page.js",
  "/survey/[caseId]/page": "app/survey/[caseId]/page.js",
  "/test-sms/page": "app/test-sms/page.js",
  "/u/[spIdentifier]/c/[token]/page": "app/u/[spIdentifier]/c/[token]/page.js",
  "/page": "app/page.js",
  "/settings/page": "app/settings/page.js",
  "/signup/page": "app/signup/page.js",
  "/search/page": "app/search/page.js"
}